bmtool/SLURM.py
bmtool/__init__.py
bmtool/__main__.py
bmtool/connectors.py
bmtool/graphs.py
bmtool/manage.py
bmtool/plot_commands.py
bmtool/singlecell.py
bmtool/synapses.py
bmtool/analysis/__init__.py
bmtool/analysis/entrainment.py
bmtool/analysis/lfp.py
bmtool/analysis/netcon_reports.py
bmtool/analysis/spikes.py
bmtool/bmplot/__init__.py
bmtool/bmplot/connections.py
bmtool/bmplot/entrainment.py
bmtool/bmplot/lfp.py
bmtool/bmplot/netcon_reports.py
bmtool/bmplot/spikes.py
bmtool/debug/__init__.py
bmtool/debug/commands.py
bmtool/debug/debug.py
bmtool/util/__init__.py
bmtool/util/commands.py
bmtool/util/util.py
bmtool/util/neuron/__init__.py
bmtool/util/neuron/celltuner.py
bmtool-0.7.9.1.dist-info/licenses/LICENSE
bmtool-0.7.9.1.dist-info/METADATA
bmtool-0.7.9.1.dist-info/WHEEL
bmtool-0.7.9.1.dist-info/entry_points.txt
bmtool-0.7.9.1.dist-info/top_level.txt
bmtool-0.7.9.1.dist-info/RECORD
