Metadata-Version: 2.4
Name: bmtool
Version: 0.7.9.1
Summary: BMTool
Home-page: https://github.com/cyneuro/bmtool
Download-URL: 
Author: Neural Engineering Laboratory at the University of Missouri
Author-email: gregglickert@mail.missouri.edu
License: MIT
Classifier: Intended Audience :: Developers
Classifier: Intended Audience :: Education
Classifier: Intended Audience :: Science/Research
Classifier: License :: OSI Approved :: MIT License
Classifier: Programming Language :: Python :: 3
Classifier: Programming Language :: Python :: 3.6
Classifier: Topic :: Software Development :: Libraries
Classifier: Topic :: Software Development :: Libraries :: Python Modules
Classifier: Operating System :: OS Independent
Requires-Python: >=3.8
License-File: LICENSE
Requires-Dist: neuron==8.2.4
Requires-Dist: bmtk
Requires-Dist: click
Requires-Dist: clint
Requires-Dist: h5py
Requires-Dist: matplotlib
Requires-Dist: networkx
Requires-Dist: numpy
Requires-Dist: pandas
Requires-Dist: questionary
Requires-Dist: pynmodlt
Requires-Dist: xarray
Requires-Dist: fooof
Requires-Dist: requests
Requires-Dist: pyyaml
Requires-Dist: PyWavelets
Requires-Dist: numba
Requires-Dist: tqdm
Provides-Extra: dev
Requires-Dist: ruff>=0.1.0; extra == "dev"
Requires-Dist: pyright>=1.1.0; extra == "dev"
Requires-Dist: pre-commit>=3.0.0; extra == "dev"
Dynamic: author
Dynamic: author-email
Dynamic: classifier
Dynamic: description
Dynamic: description-content-type
Dynamic: home-page
Dynamic: license
Dynamic: license-file
Dynamic: provides-extra
Dynamic: requires-dist
Dynamic: summary
